<?xml version="1.0" encoding="UTF-8" standalone="no"?>
<configuration>
	<feature automatic="selected" name="Name"/>
	<feature automatic="unselected" name="Dodging"/>
	<feature automatic="unselected" name="WaveSurfing"/>
	<feature automatic="unselected" name="Wall_Smoothing"/>
	<feature automatic="unselected" name="visibleEnemyWaves"/>
	<feature automatic="selected" manual="selected" name="Movement"/>
	<feature manual="selected" name="Random"/>
	<feature manual="selected" name="Firing"/>
	<feature name="GuessFactor"/>
	<feature name="DBL_Bullet_Power"/>
	<feature name="CircularTargeting"/>
	<feature name="LinearTargeting"/>
	<feature automatic="selected" manual="selected" name="Color"/>
	<feature automatic="unselected" name="BBY"/>
	<feature manual="selected" name="RBY"/>
	<feature automatic="unselected" name="GWY"/>
</configuration>
